objecttracer.py
objecttracer-1.1.0.dist-info/LICENSE
objecttracer-1.1.0.dist-info/WHEEL
objecttracer-1.1.0.dist-info/METADATA
objecttracer-1.1.0.dist-info/RECORD
