Metadata-Version: 2.1
Name: objecttracer
Version: 1.1.0
Summary: Small utility to log the activity on a given object.
License: GPL-3.0-or-later
Author: Sylvain Roy
Author-email: sylvain.roy@m4x.org
Requires-Python: >=3.7,<4.0
Classifier: License :: OSI Approved :: GNU General Public License v3 or later (GPLv3+)
Classifier: Programming Language :: Python :: 3
Classifier: Programming Language :: Python :: 3.7
Classifier: Programming Language :: Python :: 3.8
